toil/__init__.py
toil/common.py
toil/deferred.py
toil/job.py
toil/jobGraph.py
toil/leader.py
toil/realtimeLogger.py
toil/resource.py
toil/serviceManager.py
toil/statsAndLogging.py
toil/toilState.py
toil/version.py
toil/worker.py
toil/batchSystems/__init__.py
toil/batchSystems/abstractBatchSystem.py
toil/batchSystems/abstractGridEngineBatchSystem.py
toil/batchSystems/gridengine.py
toil/batchSystems/htcondor.py
toil/batchSystems/kubernetes.py
toil/batchSystems/lsf.py
toil/batchSystems/lsfHelper.py
toil/batchSystems/options.py
toil/batchSystems/parasol.py
toil/batchSystems/parasolTestSupport.py
toil/batchSystems/registry.py
toil/batchSystems/singleMachine.py
toil/batchSystems/slurm.py
toil/batchSystems/torque.py
toil/batchSystems/mesos/__init__.py
toil/batchSystems/mesos/batchSystem.py
toil/batchSystems/mesos/conftest.py
toil/batchSystems/mesos/executor.py
toil/batchSystems/mesos/test/__init__.py
toil/cwl/__init__.py
toil/cwl/conftest.py
toil/cwl/cwltoil.py
toil/fileStores/__init__.py
toil/fileStores/abstractFileStore.py
toil/fileStores/cachingFileStore.py
toil/fileStores/nonCachingFileStore.py
toil/jobStores/__init__.py
toil/jobStores/abstractJobStore.py
toil/jobStores/azureJobStore.py
toil/jobStores/conftest.py
toil/jobStores/fileJobStore.py
toil/jobStores/googleJobStore.py
toil/jobStores/utils.py
toil/jobStores/aws/__init__.py
toil/jobStores/aws/jobStore.py
toil/jobStores/aws/utils.py
toil/lib/__init__.py
toil/lib/bioio.py
toil/lib/compatibility.py
toil/lib/context.py
toil/lib/docker.py
toil/lib/ec2.py
toil/lib/ec2nodes.py
toil/lib/exceptions.py
toil/lib/expando.py
toil/lib/fnmatch.py
toil/lib/generatedEC2Lists.py
toil/lib/humanize.py
toil/lib/iterables.py
toil/lib/memoize.py
toil/lib/message.py
toil/lib/misc.py
toil/lib/objects.py
toil/lib/retry.py
toil/lib/threading.py
toil/lib/throttle.py
toil/lib/encryption/__init__.py
toil/lib/encryption/_dummy.py
toil/lib/encryption/_nacl.py
toil/lib/encryption/conftest.py
toil/provisioners/__init__.py
toil_msk-3.21.1.dist-info/LICENSE
toil_msk-3.21.1.dist-info/METADATA
toil_msk-3.21.1.dist-info/WHEEL
toil_msk-3.21.1.dist-info/entry_points.txt
toil_msk-3.21.1.dist-info/top_level.txt
toil_msk-3.21.1.dist-info/RECORD
