Metadata-Version: 2.1
Name: toil-msk
Version: 3.21.1
Summary: Pipeline management software for clusters.
Home-page: https://github.com/BD2KGenomics/toil
Author: Benedict Paten
Author-email: benedict@soe.usc.edu
License: Apache License v2.0
Platform: UNKNOWN
Classifier: Development Status :: 5 - Production/Stable
Classifier: Environment :: Console
Classifier: Intended Audience :: Developers
Classifier: Intended Audience :: Science/Research
Classifier: Intended Audience :: Healthcare Industry
Classifier: License :: OSI Approved :: Apache Software License
Classifier: Natural Language :: English
Classifier: Operating System :: MacOS :: MacOS X
Classifier: Operating System :: POSIX
Classifier: Operating System :: POSIX :: Linux
Classifier: Programming Language :: Python :: 2.7
Classifier: Programming Language :: Python :: 3.5
Classifier: Programming Language :: Python :: 3.6
Classifier: Topic :: Scientific/Engineering
Classifier: Topic :: Scientific/Engineering :: Bio-Informatics
Classifier: Topic :: Scientific/Engineering :: Astronomy
Classifier: Topic :: Scientific/Engineering :: Atmospheric Science
Classifier: Topic :: Scientific/Engineering :: Information Analysis
Classifier: Topic :: Scientific/Engineering :: Medical Science Apps.
Classifier: Topic :: System :: Distributed Computing
Classifier: Topic :: Utilities
Requires-Dist: dill (==0.2.7.1)
Requires-Dist: six (>=1.10.0)
Requires-Dist: future
Requires-Dist: requests (<3,>=2)
Requires-Dist: docker (==2.5.1)
Requires-Dist: python-dateutil
Requires-Dist: psutil (<6,>=3.0.1)
Requires-Dist: subprocess32 (<=3.5.2)
Requires-Dist: addict (<=2.2.0)
Requires-Dist: sphinx (==1.7.5)
Requires-Dist: pathlib2 (==2.3.2)
Provides-Extra: all
Requires-Dist: boto (==2.48.0) ; extra == 'all'
Requires-Dist: boto3 (<2.0,>=1.7.50) ; extra == 'all'
Requires-Dist: futures (==3.1.1) ; extra == 'all'
Requires-Dist: pycryptodome (==3.5.1) ; extra == 'all'
Requires-Dist: azure-cosmosdb-table (==0.37.1) ; extra == 'all'
Requires-Dist: secretstorage (<3) ; extra == 'all'
Requires-Dist: ansible[azure] (==2.5.0a1) ; extra == 'all'
Requires-Dist: azure-storage (==0.35.1) ; extra == 'all'
Requires-Dist: cwltool (==1.0.20190906054215) ; extra == 'all'
Requires-Dist: schema-salad (<5,>=4.5.20190815125611) ; extra == 'all'
Requires-Dist: galaxy-lib (==18.9.2) ; extra == 'all'
Requires-Dist: pynacl (==1.1.2) ; extra == 'all'
Requires-Dist: gcs-oauth2-boto-plugin (==1.14) ; extra == 'all'
Requires-Dist: apache-libcloud (==2.2.1) ; extra == 'all'
Requires-Dist: google-cloud-storage (==1.6.0) ; extra == 'all'
Requires-Dist: kubernetes (<11,>=10) ; extra == 'all'
Requires-Dist: pymesos (==0.3.7) ; extra == 'all'
Requires-Dist: psutil (<6,>=3.0.1) ; extra == 'all'
Provides-Extra: aws
Requires-Dist: boto (==2.48.0) ; extra == 'aws'
Requires-Dist: boto3 (<2.0,>=1.7.50) ; extra == 'aws'
Requires-Dist: futures (==3.1.1) ; extra == 'aws'
Requires-Dist: pycryptodome (==3.5.1) ; extra == 'aws'
Provides-Extra: azure
Requires-Dist: azure-cosmosdb-table (==0.37.1) ; extra == 'azure'
Requires-Dist: secretstorage (<3) ; extra == 'azure'
Requires-Dist: ansible[azure] (==2.5.0a1) ; extra == 'azure'
Requires-Dist: azure-storage (==0.35.1) ; extra == 'azure'
Provides-Extra: cwl
Requires-Dist: cwltool (==1.0.20190906054215) ; extra == 'cwl'
Requires-Dist: schema-salad (<5,>=4.5.20190815125611) ; extra == 'cwl'
Requires-Dist: galaxy-lib (==18.9.2) ; extra == 'cwl'
Provides-Extra: encryption
Requires-Dist: pynacl (==1.1.2) ; extra == 'encryption'
Provides-Extra: google
Requires-Dist: gcs-oauth2-boto-plugin (==1.14) ; extra == 'google'
Requires-Dist: apache-libcloud (==2.2.1) ; extra == 'google'
Requires-Dist: google-cloud-storage (==1.6.0) ; extra == 'google'
Provides-Extra: htcondor
Requires-Dist: htcondor (>=8.6.0) ; (sys_platform!="darwin") and extra == 'htcondor'
Provides-Extra: kubernetes
Requires-Dist: kubernetes (<11,>=10) ; extra == 'kubernetes'
Provides-Extra: mesos
Requires-Dist: pymesos (==0.3.7) ; extra == 'mesos'
Requires-Dist: psutil (<6,>=3.0.1) ; extra == 'mesos'
Provides-Extra: wdl
